Workbook
Name YesNoTBD: '_Lists'!$A$2:$A$5
Name QuestionStatus: '_Lists'!$B$2:$B$6
Name DeploymentModels: '_Lists'!$C$2:$C$6
Name Environments: '_Lists'!$D$2:$D$6
Name AuthenticationModes: '_Lists'!$E$2:$E$7
Name DataClassifications: '_Lists'!$F$2:$F$6
Name Priorities: '_Lists'!$G$2:$G$6
Name ReadAction: '_Lists'!$H$2:$H$6
Name InputSources: '_Lists'!$I$2:$I$5
Name ConfidenceLevels: '_Lists'!$J$2:$J$5
Name ActionTypes: '_Lists'!$K$2:$K$7
Name ActionStatus: '_Lists'!$L$2:$L$6

Sheet 00 Read Me
A1: NexoraAI Customer Discovery & Sizing Questionnaire
A2: แบบสอบถามสำหรับเก็บ Requirement, Configuration และข้อมูล Sizing — Initial scope: HR Employee Services and IT Operations
A4: Purpose / วัตถุประสงค์
A5: Use this workbook before solution design and proposal sizing. Complete customer responses, identify owners/evidence, and close open items during workshops. Yellow cells are customer-input cells.
A7: How to use / วิธีใช้
A8: 1. Complete 01–06 for organization, platform, security, knowledge and integration requirements. 2. Prioritize HR and IT Operations use cases in 07–08. 3. Complete all mandatory yellow cells in 09 Sizing Input. 4. Review 10 Sizing Summary with the solution architect. 5. Record unresolved decisions and actions in 11 Action Register.
A10: Important security instruction
A11: Do not enter passwords, tokens, API keys, client secrets, private keys, connection strings, employee records, or production log samples. Record only the owner and approved secret-store reference.
A13: Sizing disclaimer
A14: All sizing results are budgetary planning baselines—not capacity guarantees. Final production sizing requires a representative pilot/load test using the selected model, context length, document mix, RAG flow, integrations and concurrency profile.
A16: Document control
A17: Customer / ลูกค้า
A18: Project / โครงการ | B18: NexoraAI Discovery
A19: Prepared by
A20: Customer owner
A21: Workshop date
A22: Workbook version | B22: 1.0
A23: Generated | B23: 2026-09-25

Sheet 01 Organization
A1: Organization & Project Context
A2: ข้อมูลพื้นฐานโครงการ ขอบเขต สถานที่ติดตั้ง Availability และ Timeline
A4: ID | B4: Section / หมวด | C4: Question / คำถาม | D4: Why it matters / เหตุผล | E4: Required | F4: Customer response / คำตอบลูกค้า | G4: Status | H4: Owner | I4: Evidence / Reference | J4: Notes / Open issues
A5: ORG-01 | B5: Organization | C5: Legal entity and business unit in scope? / นิติบุคคลและหน่วยงานที่อยู่ในขอบเขต | D5: Defines tenancy, ownership and policy boundary. | E5: Yes | G5: Open
A6: ORG-02 | B6: Stakeholders | C6: Executive sponsor, business owner, technical owner, security owner and data owners? | D6: Required for approvals and escalation. | E6: Yes | G6: Open
A7: ORG-03 | B7: Environments | C7: Which environments are required: Sandbox, Dev, UAT, Production, DR? | D7: Drives infrastructure, licensing and release process. | E7: Yes | G7: Open
A8: ORG-04 | B8: Deployment | C8: Preferred deployment model? / รูปแบบติดตั้งที่ต้องการ | D8: Selects Azure services, Docker/VM or hybrid architecture. | E8: Yes | G8: Open
A9: ORG-05 | B9: Location | C9: Approved cloud region or on-premises data-center location? | D9: Data residency, latency and service availability. | E9: Yes | G9: Open
A10: ORG-06 | B10: Network | C10: Is user access internal-only, VPN, private network, or public HTTPS? | D10: Defines ingress, DNS, TLS and firewall design. | E10: Yes | G10: Open
A11: ORG-07 | B11: Network | C11: Is outbound Internet access allowed? If restricted, provide proxy/allowlist process (not credentials). | D11: Cloud LLM, MCP and SaaS integration connectivity. | E11: Yes | G11: Open
A12: ORG-08 | B12: Availability | C12: Required service hours, availability target and planned maintenance window? | D12: Determines topology and operational support. | E12: Yes | G12: Open
A13: ORG-09 | B13: Recovery | C13: Required RTO and RPO? / เวลากู้คืนและจุดข้อมูลที่ยอมรับได้ | D13: Defines backup, replication and DR design. | E13: Yes | G13: Open
A14: ORG-10 | B14: Growth | C14: Expected growth over 12 and 36 months for users, documents and requests? | D14: Prevents sizing only for day-one demand. | E14: Yes | G14: Open
A15: ORG-11 | B15: Support | C15: Support model, support hours and escalation contacts? | D15: Required for production operating model. | E15: No | G15: Open
A16: ORG-12 | B16: Compliance | C16: Applicable standards or regulations (e.g., PDPA, ISO 27001, SEC, internal policy)? | D16: Defines security and evidence requirements. | E16: Yes | G16: Open
A17: ORG-13 | B17: Procurement | C17: Target pilot date, production date and procurement constraints? | D17: Aligns scope and delivery sequence. | E17: Yes | G17: Open

Sheet 02 Platform Config
A1: NexoraAI Platform Configuration
A2: Identity, access, LLM, embedding, document processing, storage, retention and licensing
A4: ID | B4: Section / หมวด | C4: Question / คำถาม | D4: Why it matters / เหตุผล | E4: Required | F4: Customer response / คำตอบลูกค้า | G4: Status | H4: Owner | I4: Evidence / Reference | J4: Notes / Open issues
A5: CFG-01 | B5: URL & TLS | C5: Production DNS names and certificate source (public CA or internal PKI)? | D5: Required for HTTPS and IdP callbacks. | E5: Yes | G5: Open
A6: CFG-02 | B6: Authentication | C6: Authentication methods required? / วิธีเข้าสู่ระบบ | D6: NexoraAI supports local, Microsoft Entra ID and SAML configuration. | E6: Yes | G6: Open
A7: CFG-03 | B7: Authentication | C7: IdP owner, tenant/domain, metadata exchange process and test accounts? | D7: Required for acceptance testing; do not enter secrets. | E7: Conditional | G7: Open
A8: CFG-04 | B8: Identity | C8: Which IdP claims identify login, display name, email and groups? | D8: Required for stable identity mapping. | E8: Conditional | G8: Open
A9: CFG-05 | B9: Access | C9: List initial Teams, Team owners and approximate member counts. | D9: Defines workspace and ACL configuration. | E9: Yes | G9: Open
A10: CFG-06 | B10: Access | C10: Who may be System Admin, Team Admin, Agent Manager, Knowledge Manager and Auditor? | D10: Supports least privilege and segregation of duties. | E10: Yes | G10: Open
A11: CFG-07 | B11: LLM | C11: Cloud, local or hybrid LLM strategy? Preferred providers/models? | D11: Determines connectivity, GPU and quota sizing. | E11: Yes | G11: Open
A12: CFG-08 | B12: LLM | C12: Required model capabilities: tools/function calling, vision, languages, context length, reasoning? | D12: Agent and attachment feature compatibility. | E12: Yes | G12: Open
A13: CFG-09 | B13: LLM | C13: Provider quota: TPM, RPM, concurrent requests and regional capacity? | D13: Often the primary cloud-LLM bottleneck. | E13: Conditional | G13: Open
A14: CFG-10 | B14: Embedding | C14: Preferred embedding provider/model and data-residency constraint? | D14: Controls index compatibility and re-index planning. | E14: Yes | G14: Open
A15: CFG-11 | B15: Document processing | C15: Native parsing, Azure Document Intelligence or local OCR required? | D15: Driven by scanned documents, Thai and complex layouts. | E15: Yes | G15: Open
A16: CFG-12 | B16: Storage | C16: Approved storage: Azure services, local Mongo/MinIO/Qdrant, or hybrid? | D16: Defines stateful services and backup scope. | E16: Yes | G16: Open
... A19: CFG-15 | B19: Observability | C19: Preferred monitoring platform and required application/infrastructure metrics? | D19: Defines system health integration and alerts. | E19: No | G19: Open

Sheet 03 Security
A1: Security, Privacy & Governance
A2: ข้อมูล Classification, PII/DLP, encryption, secrets, ACL, audit และ security acceptance
A4: ID | B4: Section / หมวด | C4: Question / คำถาม | D4: Why it matters / เหตุผล | E4: Required | F4: Customer response / คำตอบลูกค้า | G4: Status | H4: Owner | I4: Evidence / Reference | J4: Notes / Open issues
A5: SEC-01 | B5: Data | C5: Highest data classification permitted in the platform? | D5: Sets baseline controls and eligible use cases. | E5: Yes | G5: Open
A6: SEC-02 | B6: Data | C6: Which PII, payroll, health, performance or regulated fields are prohibited or restricted? | D6: Required for HR boundaries, guardrails and logging. | E6: Yes | G6: Open
A7: SEC-03 | B7: Encryption | C7: Encryption requirements at rest and in transit; approved ciphers/certificate policy? | D7: Defines platform and infrastructure controls. | E7: Yes | G7: Open
A8: SEC-04 | B8: Key management | C8: Approved key/secret store, rotation interval and key custodians? | D8: Covers APP_DATA_ENCRYPTION_KEY, provider secrets and certificates. | E8: Yes | G8: Open
A9: SEC-05 | B9: Network | C9: Required segmentation, private endpoints, firewall, WAF or reverse proxy? | D9: Defines production network architecture. | E9: Yes | G9: Open
A10: SEC-06 | B10: Guardrails | C10: Required PII/DLP categories, block/redact/warn behavior and exception approver? | D10: Creates reusable enforced guardrail profiles. | E10: Yes | G10: Open
A11: SEC-07 | B11: Knowledge ACL | C11: Required document ACL granularity: personal, Team, Data Group, global? | D11: NexoraAI enforces retrieval authorization server-side. | E11: Yes | G11: Open
A12: SEC-08 | B12: Tools | C12: Which integrations/actions are read-only, approval-gated or prohibited? | D12: Defines tool policy and risk boundary. | E12: Yes | G12: Open
A13: SEC-09 | B13: Audit | C13: Audit events, viewers, export target and retention period? | D13: Supports investigation and compliance evidence. | E13: Yes | G13: Open
A14: SEC-10 | B14: Logging | C14: What content must never appear in logs or telemetry? | D14: Prevents prompt/tool/secret leakage. | E14: Yes | G14: Open
A15: SEC-11 | B15: Files | C15: Required malware scanning, file types, maximum size and quarantine process? | D15: Controls attachment and Knowledge ingestion risk. | E15: Yes | G15: Open
A16: SEC-12 | B16: Vendor risk | C16: Are cloud LLM data processing, retention and training terms approved? | D16: Determines eligible providers and deployment mode. | E16: Conditional | G16: Open
... A18: SEC-14 | B18: Incident | C18: Security incident owner, reporting SLA and evidence preservation process? | D18: Required for operating model. | E18: No | G18: Open

Sheet 04 Knowledge & Data
A1: Knowledge, Documents & Data
A2: แหล่งข้อมูล ปริมาณ รูปแบบ ภาษา OCR, ACL, freshness และ evaluation dataset
A4: ID | B4: Section / หมวด | C4: Question / คำถาม | D4: Why it matters / เหตุผล | E4: Required | F4: Customer response / คำตอบลูกค้า | G4: Status | H4: Owner | I4: Evidence / Reference | J4: Notes / Open issues
A5: KN-01 | B5: Sources | C5: List policy, procedure, runbook, architecture, known-error and FAQ repositories. | D5: Defines initial Knowledge migration scope. | E5: Yes | G5: Open
A6: KN-02 | B6: Formats | C6: File types and typical content: PDF, Word, Excel, PowerPoint, HTML, images, scans? | D6: Determines extraction and OCR path. | E6: Yes | G6: Open
A7: KN-03 | B7: Volume | C7: Current document count, pages, total GB and average file size? | D7: Primary storage and ingestion sizing input. | E7: Yes | G7: Open
A8: KN-04 | B8: Growth | C8: New/updated documents per day/month and expected annual growth? | D8: Worker and storage sizing. | E8: Yes | G8: Open
A9: KN-05 | B9: Languages | C9: Languages and percentage of Thai/English/multilingual content? | D9: Affects OCR, embedding and evaluation. | E9: Yes | G9: Open
A10: KN-06 | B10: Scans | C10: Percentage scanned/image-only and percentage with tables/complex layouts? | D10: Determines OCR/document intelligence load. | E10: Yes | G10: Open
A11: KN-07 | B11: Ownership | C11: Document owners, approvers and review/expiry cadence? | D11: Keeps answers current and accountable. | E11: Yes | G11: Open
A12: KN-08 | B12: ACL | C12: How are users mapped to document access today? | D12: Defines Team/Data Group assignment and migration. | E12: Yes | G12: Open
A13: KN-09 | B13: Quality | C13: Required citation format, page/section evidence and confidence threshold? | D13: Defines response and acceptance quality. | E13: Yes | G13: Open
A14: KN-10 | B14: Lifecycle | C14: Archive, deletion, legal hold and source-of-truth synchronization rules? | D14: Prevents stale or unauthorized retrieval. | E14: Yes | G14: Open
A15: KN-11 | B15: Evaluation | C15: Provide representative questions, approved answers and negative tests. | D15: Creates RAG evaluation dataset. | E15: Yes | G15: Open
A16: KN-12 | B16: Freshness | C16: Maximum acceptable delay from source update to searchable Knowledge? | D16: Defines ingestion SLA. | E16: No | G16: Open

Sheet 05 Integrations
A1: Integrations & MCP Discovery
A2: ระบบปลายทาง การเชื่อมต่อ สิทธิ์ tenant mapping, rate limit และ approval boundary
A4: ID | B4: Section / หมวด | C4: Question / คำถาม | D4: Why it matters / เหตุผล | E4: Required | F4: Customer response / คำตอบลูกค้า | G4: Status | H4: Owner | I4: Evidence / Reference | J4: Notes / Open issues
A5: INT-01 | B5: Inventory | C5: List required systems and owners: HRIS, Service Desk, CMDB, Datadog/observability, cloud, collaboration, email. | D5: Creates integration roadmap and ownership. | E5: Yes | G5: Open
A6: INT-02 | B6: Connection | C6: For each system, is an official hosted MCP, customer-managed MCP, REST API, database or file exchange available? | D6: Determines connection architecture. | E6: Yes | G6: Open
A7: INT-03 | B7: Environment | C7: Provide non-production endpoints/tenants and network route owner (no secrets). | D7: Required for safe integration testing. | E7: Yes | G7: Open
A8: INT-04 | B8: Authentication | C8: Supported auth: OAuth/OIDC, service principal, PAT/SAT, API key, mTLS? Record owner only. | D8: Determines credential lifecycle. | E8: Yes | G8: Open
A9: INT-05 | B9: Authorization | C9: Required scopes/roles and Team/tenant mapping? | D9: Supports least privilege and tenant isolation. | E9: Yes | G9: Open
A10: INT-06 | B10: Rate limits | C10: API/MCP rate limits, quotas, result limits and maintenance windows? | D10: Affects runtime and retry behavior. | E10: No | G10: Open
A11: INT-07 | B11: Actions | C11: Which operations may change external systems? Who approves each action? | D11: Separates read-only analysis from governed action. | E11: Yes | G11: Open
A12: INT-08 | B12: Datadog | C12: Datadog site, tenant count, Team ownership, available toolsets and approved read tools? | D12: Each tenant should be a separate Team-assigned connection. | E12: Conditional | G12: Open
A13: INT-09 | B13: ITSM | C13: ServiceNow/Jira projects, ticket fields, status flow and change approval process? | D13: Required for incident/change workflows. | E13: Conditional | G13: Open
A14: INT-10 | B14: HRIS | C14: HR system, employee self-service APIs and fields permitted for read/action? | D14: Extends Knowledge-only HR into transactions safely. | E14: Conditional | G14: Open
A15: INT-11 | B15: Testing | C15: Integration test data, test accounts and acceptance scenarios? | D15: Required for end-to-end validation. | E15: Yes | G15: Open
A16: INT-12 | B16: Failure | C16: Expected behavior when integration is unavailable or returns incomplete data? | D16: Defines safe fallback and user messaging. | E16: Yes | G16: Open

Sheet 06 Operations
A1: Deployment & Operating Model
A2: Topology, backup/restore, monitoring, patching, release, DR และ RACI
A4: ID | B4: Section / หมวด | C4: Question / คำถาม | D4: Why it matters / เหตุผล | E4: Required | F4: Customer response / คำตอบลูกค้า | G4: Status | H4: Owner | I4: Evidence / Reference | J4: Notes / Open issues
A5: OPS-01 | B5: Topology | C5: Single-host pilot or production HA/multi-node requirement? | D5: Compose is suitable for pilot; HA requires separated tiers. | E5: Yes | G5: Open
A6: OPS-02 | B6: Backup | C6: Backup destination, frequency, retention, encryption and owner? | D6: Covers MongoDB, object storage, vectors and configuration. | E6: Yes | G6: Open
A7: OPS-03 | B7: Restore | C7: Restore test frequency and evidence required? | D7: Backup is not complete until restore is tested. | E7: Yes | G7: Open
A8: OPS-04 | B8: Monitoring | C8: CPU, memory, disk, queue, provider quota, worker backlog and certificate alerts? | D8: System Health is on-demand, not continuous monitoring. | E8: Yes | G8: Open
A9: OPS-05 | B9: Logs | C9: Central log/SIEM destination and retention? | D9: Supports operations and audit without sensitive content. | E9: Yes | G9: Open
A10: OPS-06 | B10: Patching | C10: OS/container/model patch cadence and vulnerability response SLA? | D10: Defines operational security. | E10: Yes | G10: Open
A11: OPS-07 | B11: Release | C11: Dev/UAT/Prod promotion, rollback and change approval process? | D11: Defines deployment governance. | E11: Yes | G11: Open
A12: OPS-08 | B12: Capacity | C12: Who monitors p95 latency, queue depth, throttling, GPU utilization and ingestion backlog? | D12: These signals trigger scaling decisions. | E12: Yes | G12: Open
A13: OPS-09 | B13: DR | C13: DR site/region, failover method and test frequency? | D13: Required where RTO/RPO cannot be met on one host. | E13: Conditional | G13: Open
A14: OPS-10 | B14: Ownership | C14: RACI for application, infrastructure, database, vector store, storage, LLM and integrations? | D14: Avoids support ownership gaps. | E14: Yes | G14: Open

Sheet 07 HR Use Cases
A1: HR Employee Services — Use Case Discovery
A2: Prioritize Knowledge-only guidance separately from HRIS actions; never use chat to disclose another employee's confidential data.
A4: Use case ID | B4: Candidate use case | C4: Example user request | D4: Priority | E4: Personas / Users | F4: Monthly volume | G4: Current process & pain | H4: Knowledge sources | I4: System of record / Integration | J4: Read or Action | K4: Approval required | L4: Data classification | M4: Success metric / Target | N4: Scope decision / Notes
A5: HR-01 | B5: Policy and FAQ assistant | C5: What is the annual leave carry-forward policy, and when does it expire?
A6: HR-02 | B6: Benefits and eligibility guidance | C6: Am I eligible for this benefit and what conditions apply?
A7: HR-03 | B7: Learning request guidance | C7: What approvals and documents are required before purchasing a course?
A8: HR-04 | B8: Employment letter request | C8: How do I request an English employment letter with salary information?
A9: HR-05 | B9: Hybrid/overseas work guidance | C9: Can I work from another country, and who must approve it?
A10: HR-06 | B10: Onboarding assistant | C10: Give a role-based onboarding checklist for a new employee.
A11: HR-07 | B11: HR case triage | C11: Classify my request and route it to the correct HR service queue.
A12: HR-08 | B12: Employee self-service transaction | C12: Show my own leave balance or submit a request after confirmation.
A13: HR-09 | B13: Manager guidance | C13: What process should a manager follow for a policy exception?
A14: HR-10 | B14: Privacy and missing-evidence handling | C14: Refuse unauthorized employee data and escalate when policy evidence is absent.

Sheet 08 IT Ops Use Cases
A1: IT Operations — Use Case Discovery
A2: Separate observation, recommendation and action. Production-changing tools should be read-only or approval-gated by policy.
A4: Use case ID | B4: Candidate use case | C4: Example user request | D4: Priority | E4: Personas / Users | F4: Monthly volume | G4: Current process & pain | H4: Knowledge sources | I4: System of record / Integration | J4: Read or Action | K4: Approval required | L4: Data classification | M4: Success metric / Target | N4: Scope decision / Notes
A5: IT-01 | B5: Alert and incident triage | C5: Summarize active critical alerts for production services and rank likely impact.
A6: IT-02 | B6: Slow application investigation | C6: Correlate RUM, APM, database, infrastructure, logs, changes and tickets.
A7: IT-03 | B7: Knowledge/runbook recommendation | C7: Find the approved runbook and known-error record matching this evidence.
A8: IT-04 | B8: Evidence timeline | C8: Build a timestamped incident timeline with source links and confidence.
A9: IT-05 | B9: Severity trend chart | C9: Chart alerts by severity for the last three months using exact Datadog results.
A10: IT-06 | B10: Service Desk enrichment | C10: Draft or update an incident with evidence, affected service and suggested next steps.
A11: IT-07 | B11: Change-risk correlation | C11: Identify recent changes correlated with degradation; do not assert causation without evidence.
A12: IT-08 | B12: Approval-ready remediation | C12: Prepare a reversible action plan, validation steps and rollback criteria.
A13: IT-09 | B13: Cloud inventory and architecture | C13: Read approved cloud inventory and create an evidence-labelled architecture diagram.
A14: IT-10 | B14: Post-incident review | C14: Draft an evidence-backed PIR with gaps and follow-up actions.

Sheet 09 Sizing Input
A1: Sizing Input
A2: Complete yellow cells. Use measured pilot values where available; otherwise mark the source as Planning assumption.
A4: ID | B4: Sizing input | C4: Unit | D4: Customer value | E4: Mandatory | F4: Source | G4: Confidence | H4: Guidance / Notes
A5: SZ-01 | B5: Total named users | C5: users | E5: Yes | H5: Licensing and identity population; not a throughput measure.
A6: SZ-02 | B6: Monthly active users | C6: users | E6: Yes | H6: Users expected to submit at least one request per month.
A7: SZ-03 | B7: Peak concurrent users | C7: users | E7: Yes | H7: Users actively using the portal at the same time.
A8: SZ-04 | B8: Peak simultaneous LLM generations | C8: generations | E8: Yes | H8: Most important runtime concurrency input; measure during pilot.
A9: SZ-05 | B9: Average AI requests per active user per day | C9: requests/day | E9: Yes | H9: Include Chat, Ask and agent workflows.
A10: SZ-06 | B10: Peak-hour traffic share | C10: % of daily | E10: Yes | H10: Percentage of daily requests occurring in the busiest hour.
A11: SZ-07 | B11: Average input/context tokens per request | C11: tokens | E11: Yes | H11: Include prompt, conversation, RAG excerpts and tool context.
A12: SZ-08 | B12: Average output tokens per request | C12: tokens | E12: Yes | H12: Use measured completion tokens where available.
A13: SZ-09 | B13: Target p95 end-to-end response time | C13: seconds | E13: Yes | H13: Includes retrieval, tools and model response.
A14: SZ-10 | B14: Cloud LLM provider TPM quota | C14: tokens/min | E14: Conditional | H14: Enter approved quota; leave blank for local-only.
A15: SZ-11 | B15: Cloud LLM provider RPM quota | C15: requests/min | E15: Conditional | H15: Enter approved quota; leave blank for local-only.
A16: SZ-12 | B16: Current Knowledge documents | C16: documents | E16: Yes | H16: Count unique source files.
... A34: SZ-30 | B34: Required free-disk headroom | C34: % | E34: Yes | H34: Recommended minimum is 25%.

Sheet 10 Sizing Summary
A1: Indicative Sizing Summary
A2: Formula-driven planning view. Review with a solution architect and validate by representative load testing before proposal commitment.
A4: Category | B4: Metric | C4: Calculated value | D4: Unit | E4: Planning interpretation | F4: Status | G4: Owner / Next action
A5: Completeness | B5: Mandatory inputs completed | C5: =COUNTIFS('09 Sizing Input'!E5:E34,"Yes",'09 Sizing Input'!D5:D34,"<>") | D5: of mandatory | E5: Complete required inputs before relying on sizing. | F5: =IF(C5=COUNTIF('09 Sizing Input'!E5:E34,"Yes"),"Ready","Incomplete")
A6: Demand | B6: Estimated AI requests per business day | C6: =IFERROR('09 Sizing Input'!D6*'09 Sizing Input'!D9,0) | D6: requests/day | E6: Monthly active users × average daily requests. | F6: =IF(C6>0,"Calculated","Input needed")
A7: Demand | B7: Estimated busiest-hour requests | C7: =IFERROR(C6*'09 Sizing Input'!D10/100,0) | D7: requests/hour | E7: Apply peak-hour share to daily requests. | F7: =IF(C7>0,"Calculated","Input needed")
A8: Demand | B8: Estimated busiest-hour RPM | C8: =IFERROR(C7/60,0) | D8: requests/min | E8: Compare with provider RPM and measured workflow behavior. | F8: =IF(C8>0,"Calculated","Input needed")
A9: LLM | B9: Estimated average token demand | C9: =IFERROR(C8*('09 Sizing Input'!D11+'09 Sizing Input'!D12),0) | D9: tokens/min | E9: Planning average during busiest hour; add burst and retry allowance. | F9: =IF(C9>0,"Calculated","Input needed")
A10: LLM | B10: Recommended quota with 30% headroom | C10: =ROUNDUP(C9*1.3,0) | D10: tokens/min | E10: Compare with approved cloud TPM quota. | F10: =IF(C10=0,"Input needed",IF(OR('09 Sizing Input'!D14="",'09 Sizing Input'!D14=0),"Quota not supplied",IF(C10<='09 Sizing Input'!D14,"Within supplied quota","Quota gap")))
A11: Concurrency | B11: 12-month simultaneous generations | C11: =ROUNDUP(IFERROR('09 Sizing Input'!D8*(1+'09 Sizing Input'!D33/100),0),0) | D11: generations | E11: Primary runtime scaling input; validate p95 and queue depth. | F11: =IF(C11>0,"Calculated","Input needed")
A12: Storage | B12: Current source documents | C12: =IFERROR('09 Sizing Input'!D16*'09 Sizing Input'!D17/1024,0) | D12: GiB | E12: Raw source data only; excludes vectors, metadata and backups. | F12: =IF(C12>0,"Calculated","Input needed")
A13: Storage | B13: 12-month source documents | C13: =IFERROR(C12*(1+'09 Sizing Input'!D18/100),0) | D13: GiB | E13: Raw documents after annual growth. | F13: =IF(C13>0,"Calculated","Input needed")
A14: Storage | B14: Retained private attachments | C14: =IFERROR('09 Sizing Input'!D6*'09 Sizing Input'!D22*'09 Sizing Input'!D23*('09 Sizing Input'!D24/30)/1024,0) | D14: GiB | E14: Approximation based on monthly uploads and retention. | F14: =IF(C14>=0,"Calculated","Input needed")
A15: Storage | B15: Primary data planning capacity | C15: =IFERROR((C13*1.75+C14)*1.25,0) | D15: GiB | E15: Includes indicative vector/metadata overhead and 25% operating margin. | F15: =IF(C15>0,"Budgetary","Input needed")
A16: Storage | B16: Storage including retained backup copies | C16: =IFERROR(C15*(1+'09 Sizing Input'!D25),0) | D16: GiB | E16: Budget across primary and retained copies; placement may be separate. | F16: =IF(C16>0,"Budgetary","Input needed")
A17: Ingestion | B17: Steady-state pages per business day | C17: =IFERROR('09 Sizing Input'!D21*'09 Sizing Input'!D19,0) | D17: pages/day | E17: Use OCR share to plan worker throughput. | F17: =IF(C17>0,"Calculated","Input needed")
A18: GPU | B18: Indicative local GPU VRAM incl. 20% margin | C18: =IFERROR('09 Sizing Input'!D30*'09 Sizing Input'!D31*1.2,0) | D18: GiB total | E18: Only valid with measured VRAM per replica; does not select GPU SKU. | F18: =IF(OR('09 Sizing Input'!D28="Local / On-premises",'09 Sizing Input'!D28="Hybrid"),IF(C18>0,"Budgetary","Measurement needed"),"Not required")
A19: Infrastructure | B19: Initial infrastructure tier | C19: =IF(OR('09 Sizing Input'!D8="",'09 Sizing Input'!D8=0),"Input needed",IF('09 Sizing Input'!D8<=10,"Pilot / light cloud-LLM",IF('09 Sizing Input'!D8<=30,"Small production baseline",IF('09 Sizing Input'!D8<=75,"Scale-out production baseline","Capacity engineering required")))) | D19: tier | E19: See Recommended Baseline below; not a capacity guarantee. | F19: =IF(C19="Input needed","Incomplete","Review")
B22: Recommended baseline (budgetary)
B23: Tier | C23: Starting application baseline | D23: Data disk | E23: Topology / Important condition
B24: Pilot / light cloud-LLM | C24: 8 vCPU / 32 GiB RAM | D24: 256 GiB SSD | E24: Single host acceptable for evaluation; no HA guarantee.
B25: Small production baseline | C25: Start 16 vCPU / 64 GiB RAM | D25: 512 GiB SSD | E25: Use cloud LLM or separately sized local inference; validate concurrency.
B26: Scale-out production baseline | C26: 2+ app/worker nodes; size each from load test | D26: 512 GiB+ managed or replicated storage | E26: Separate app, worker, data and inference tiers; remove single points of failure.
B27: Capacity engineering required | C27: Architecture and load-test exercise | D27: Based on measured working set and retention | E27: Model, context, tools, OCR, HA and growth materially affect design.

Sheet 11 Action Register
A1: Decision & Action Register
A2: Track missing information, customer decisions, risks and follow-up evidence discovered during workshops.
A4: Action ID | B4: Type | C4: Related question/use case | D4: Description | E4: Owner | F4: Due date | G4: Status | H4: Priority | I4: Decision / Evidence | J4: Notes
A5: ACT-001 | G5: Open
A6: ACT-002 | G6: Open
A7: ACT-003 | G7: Open
A8: ACT-004 | G8: Open
A9: ACT-005 | G9: Open
A10: ACT-006 | G10: Open
A11: ACT-007 | G11: Open
A12: ACT-008 | G12: Open
A13: ACT-009 | G13: Open
A14: ACT-010 | G14: Open
A15: ACT-011 | G15: Open
A16: ACT-012 | G16: Open
... A34: ACT-030 | G34: Open

Sheet _Lists
A1: YesNoTBD | B1: QuestionStatus | C1: DeploymentModels | D1: Environments | E1: AuthenticationModes | F1: DataClassifications | G1: Priorities | H1: ReadAction | I1: InputSources | J1: ConfidenceLevels | K1: ActionTypes | L1: ActionStatus
A2: Yes | B2: Open | C2: Azure managed services | D2: Sandbox only | E2: Microsoft Entra ID | F2: Public | G2: Must have | H2: Read-only | I2: Customer measured | J2: High | K2: Information | L2: Open
A3: No | B3: In progress | C3: Azure VM + Docker Compose | D3: Dev + UAT | E3: SAML 2.0 | F3: Internal | G3: Should have | H3: Draft only | I3: Customer estimate | J3: Medium | K3: Decision | L3: In progress
A4: To be confirmed | B4: Answered | C4: Local / On-premises | D4: Dev + UAT + Production | E4: Local authentication | F4: Confidential | G4: Could have | H4: Action with approval | I4: Planning assumption | J4: Low | K4: Risk | L4: Blocked
A5: Not applicable | B5: Evidence pending | C5: Hybrid | D5: Dev + UAT + Production + DR | E5: Entra ID + Local break-glass | F5: Restricted / Regulated | G5: Out of scope | H5: Automatic action | I5: Pilot measurement pending | J5: Unknown | K5: Dependency | L5: Completed
B6: Not applicable | C6: To be confirmed | D6: To be confirmed | E6: SAML + Local break-glass | F6: To be confirmed | G6: To be confirmed | H6: Not applicable | K6: Test | L6: Cancelled
E7: Multiple / To be confirmed | K7: Security review
